
{
  "orders": [
  {
    "id": "ORD-1001",
    "orderDate": "2025-01-12",
    "quantity": 500,
    "unitCost": 25,
    "status": "delivered"
  },
  {
    "id": "ORD-1002",
    "orderDate": "2025-02-03",
    "quantity": 300,
    "unitCost": 30,
    "status": "delivered"
  },
  {
    "id": "ORD-1003",
    "orderDate": "2025-03-18",
    "quantity": 450,
    "unitCost": 22,
    "status": "confirmed"
  },
  {
    "id": "ORD-1004",
    "orderDate": "2025-04-09",
    "quantity": 700,
    "unitCost": 28,
    "status": "confirmed"
  },
  {
    "id": "ORD-1005",
    "orderDate": "2025-05-20",
    "quantity": 600,
    "unitCost": 35,
    "status": "planned"
  },
  {
    "id": "ORD-1006",
    "orderDate": "2025-06-25",
    "quantity": 800,
    "unitCost": 27,
    "status": "planned"
  },
  {
    "id": "ORD-1007",
    "orderDate": "2025-07-14",
    "quantity": 900,
    "unitCost": 24,
    "status": "planned"
  },
  {
    "id": "ORD-1008",
    "orderDate": "2025-08-30",
    "quantity": 650,
    "unitCost": 29,
    "status": "planned"
  }
],
  
 "stockData": [
  { "month": "2025-01-01", "stockLevel": 1540, "demand": 950, "projected": false },
  { "month": "2025-02-01", "stockLevel": 1565, "demand": 970, "projected": false },
  { "month": "2025-03-01", "stockLevel": 1680, "demand": 1100, "projected": false },
  { "month": "2025-04-01", "stockLevel": 1720, "demand": 1050, "projected": false },
  { "month": "2025-05-01", "stockLevel": 1685, "demand": 1020, "projected": false },
  { "month": "2025-06-01", "stockLevel": 1670, "demand": 980, "projected": false },
  { "month": "2025-07-01", "stockLevel": 1690, "demand": 1000, "projected": false },
  { "month": "2025-08-01", "stockLevel": 1745, "demand": 1080, "projected": false },
  { "month": "2025-09-01", "stockLevel": 1800, "demand": 1150, "projected": true },
  { "month": "2025-10-01", "stockLevel": 1855, "demand": 1180, "projected": true },
  { "month": "2025-11-01", "stockLevel": 1890, "demand": 1200, "projected": true },
  { "month": "2025-12-01", "stockLevel": 1940, "demand": 1250, "projected": true }
]



  
}